__init__.py
s3ssion.py
s3ssion-1.0.2.dist-info/LICENSE
s3ssion-1.0.2.dist-info/METADATA
s3ssion-1.0.2.dist-info/WHEEL
s3ssion-1.0.2.dist-info/top_level.txt
s3ssion-1.0.2.dist-info/RECORD
