Metadata-Version: 2.1
Name: s3ssion
Version: 1.0.2
Summary: Login Session Manager
Author-email: Soumyo Deep Gupta <deep.main.ac@gmail.com>
Maintainer-email: Soumyo Deep Gupta <deep.main.ac@gmail.com>
License: MIT License
Project-URL: Homepage, https://github.com/d33pster/s3ssion
Project-URL: Issues, https://github.com/d33pster/s3ssion/issues
Keywords: d33pster,login,session,session-manager,login-manager,login-screen
Classifier: Development Status :: 4 - Beta
Classifier: Intended Audience :: Developers
Classifier: Programming Language :: Python :: 3.9
Classifier: Programming Language :: Python :: 3.10
Classifier: Programming Language :: Python :: 3.11
Classifier: Programming Language :: Python :: 3.12
Classifier: License :: OSI Approved :: MIT License
Classifier: Operating System :: OS Independent
Requires-Python: >=3.9
License-File: LICENSE
Requires-Dist: cryptography
